{
  "strategy_name": "kumo_breakout",
  "params": {
    "trailing": {
      "trailing_stop": false,
      "trailing_stop_positive": null,
      "trailing_stop_positive_offset": 0.0,
      "trailing_only_offset_is_reached": false
    },
    "buy": {},
    "sell": {},
    "protection": {},
    "roi": {
      "0": 0.14300000000000002,
      "39": 0.064,
      "60": 0.039,
      "180": 0
    },
    "stoploss": {
      "stoploss": -0.347
    }
  },
  "ft_stratparam_v": 1,
  "export_time": "2022-10-08 10:08:16.880149+00:00"
}